{
    "RO": {
        "now": "2023-08-30T15:00:00",
        "temp": 17.5
    },
    "GEMCanada": [
        {
            "now": "2023-08-30T15:00:00",
            "temp": 30.3
        },
        {
            "now": "2023-08-30T21:00:00",
            "temp": 25.4
        },
        {
            "now": "2023-08-31T03:00:00",
            "temp": 20.7
        },
        {
            "now": "2023-08-31T09:00:00",
            "temp": 23.0
        },
        {
            "now": "2023-08-31T15:00:00",
            "temp": 27.7
        },
        {
            "now": "2023-08-31T21:00:00",
            "temp": 22.4
        },
        {
            "now": "2023-09-01T03:00:00",
            "temp": 19.1
        },
        {
            "now": "2023-09-01T09:00:00",
            "temp": 20.3
        },
        {
            "now": "2023-09-01T15:00:00",
            "temp": 25.8
        },
        {
            "now": "2023-09-01T21:00:00",
            "temp": 20.3
        },
        {
            "now": "2023-09-02T03:00:00",
            "temp": 14.5
        },
        {
            "now": "2023-09-02T09:00:00",
            "temp": 17.8
        },
        {
            "now": "2023-09-02T15:00:00",
            "temp": 27.5
        },
        {
            "now": "2023-09-02T21:00:00",
            "temp": 21.9
        },
        {
            "now": "2023-09-03T03:00:00",
            "temp": 16.4
        },
        {
            "now": "2023-09-03T09:00:00",
            "temp": 21.3
        },
        {
            "now": "2023-09-03T15:00:00",
            "temp": 30.3
        },
        {
            "now": "2023-09-03T21:00:00",
            "temp": 23.7
        },
        {
            "now": "2023-09-04T03:00:00",
            "temp": 20.0
        },
        {
            "now": "2023-09-04T09:00:00",
            "temp": 23.6
        },
        {
            "now": "2023-09-04T15:00:00",
            "temp": 30.5
        },
        {
            "now": "2023-09-04T21:00:00",
            "temp": 21.6
        },
        {
            "now": "2023-09-05T03:00:00",
            "temp": 16.2
        },
        {
            "now": "2023-09-05T09:00:00",
            "temp": 15.6
        },
        {
            "now": "2023-09-05T15:00:00",
            "temp": 21.7
        },
        {
            "now": "2023-09-05T21:00:00",
            "temp": 16.7
        }
    ]
}